SiQ3D/__init__.py
SiQ3D/classifiers.py
SiQ3D/immuneTracker.py
SiQ3D/preprocess.py
SiQ3D/segmentation.py
SiQ3D/track.py
SiQ3D/tumorTracker.py
SiQ3D/unet3d.py
SiQ3D-0.1.0.dist-info/LICENSE
SiQ3D-0.1.0.dist-info/METADATA
SiQ3D-0.1.0.dist-info/WHEEL
SiQ3D-0.1.0.dist-info/top_level.txt
SiQ3D-0.1.0.dist-info/RECORD
