Metadata-Version: 2.1
Name: SiQ3D
Version: 0.1.0
Summary: Deep Learning-based 3D single-cell imaging analysis pipeline for quantifying cell-cell interaction dynamics
Home-page: https://github.com/simonlbd1/SiQ-3D
Author: Simon lbd
Author-email: simonlbd123@gmail.com
Classifier: Programming Language :: Python
Classifier: Environment :: GPU :: NVIDIA CUDA
Requires-Python: >=3.8
License-File: LICENSE
Requires-Dist: btrack (==0.4.3)
Requires-Dist: h5py (==3.1.0)
Requires-Dist: matplotlib (==3.5.3)
Requires-Dist: notebook (==6.5.2)
Requires-Dist: numpy (==1.19.5)
Requires-Dist: opencv-python (==4.6.0.66)
Requires-Dist: pandas (==1.4.3)
Requires-Dist: pillow (==9.2.0)
Requires-Dist: protobuf (==3.20.3)
Requires-Dist: scikit-image (==0.19.3)
Requires-Dist: scikit-learn (==1.1.3)
